setup.py
htmlgrab/__init__.py
htmlgrab.egg-info/PKG-INFO
htmlgrab.egg-info/SOURCES.txt
htmlgrab.egg-info/dependency_links.txt
htmlgrab.egg-info/top_level.txt
htmlgrab/bin/__init__.py
htmlgrab/bin/html-grab.py
htmlgrab/core/__init__.py