Metadata-Version: 1.0
Name: htmlgrab
Version: 0.0.3-alpha
Summary: A simple command line script to generate static web pages.
Home-page: https://github.com/iepsen/python-htmlgrab
Author: Marcelo Iepsen
Author-email: iepsen@gmail.com
License: MIT
Download-URL: http://pypi.python.org/packages/source/h/htmlgrab/htmlgrab-0.0.3-alpha.tar.gz
Keywords: python,html,grab
Platform: UNKNOWN
